mcp_marketplace/__init__.py
mcp_marketplace/base.py
mcp_marketplace/cli.py
mcp_marketplace/config.py
mcp_marketplace/constants.py
mcp_marketplace/utils.py
mcp_marketplace/app/__init__.py
mcp_marketplace/app/mcp_tool_use/__init__.py
mcp_marketplace/app/mcp_tool_use/data/mcp/config/mcp_config.json
mcp_marketplace/app/mcp_tool_use/data/mcp/config/category/mcp_config_browser.json
mcp_marketplace/app/mcp_tool_use/data/mcp/config/category/mcp_config_finance.json
mcp_marketplace/app/mcp_tool_use/data/mcp/config/category/mcp_config_map.json
mcp_marketplace/app/mcp_tool_use/data/mcp/config/category/mcp_config_search.json
mcp_marketplace/app/mcp_tool_use/data/mcp/config/category/mcp_database.json
mcp_marketplace/app/mcp_tool_use/data/mcp/config/category/mcp_payment.json
mcp_marketplace/app/mcp_tool_use/src/__init__.py
mcp_marketplace/app/mcp_tool_use/src/app.py
mcp_marketplace/app/mcp_tool_use/src/constants.py
mcp_marketplace/app/mcp_tool_use/src/global_variables.py
mcp_marketplace/app/mcp_tool_use/src/mcp_servers.py
mcp_marketplace/app/mcp_tool_use/src/mock.py
mcp_marketplace/app/mcp_tool_use/src/msg_system.py
mcp_marketplace/app/mcp_tool_use/src/prompts.py
mcp_marketplace/app/mcp_tool_use/src/utils.py
mcp_marketplace/app/mcp_tool_use/src/claude/__init__.py
mcp_marketplace/app/mcp_tool_use/src/claude/claude_api.py
mcp_marketplace/app/mcp_tool_use/src/core/__init__.py
mcp_marketplace/app/mcp_tool_use/src/core/workflow.py
mcp_marketplace/app/mcp_tool_use/src/openai/__init__.py
mcp_marketplace/app/mcp_tool_use/src/openai/gpt_api.py
mcp_marketplace/app/mcp_tool_use/src/qwen/__init__.py
mcp_marketplace/app/mcp_tool_use/src/qwen/qwen_general_api.py
mcp_marketplace/app/mcp_tool_use/tests/__init__.py
mcp_marketplace/app/mcp_tool_use/tests/run_mcp_request.py
mcp_marketplace/app/mcp_tool_use/web/plugin/agent_toolbox/scripts.js
mcp_marketplace/app/mcp_tool_use/web/plugin/agent_toolbox/styles.css
mcp_marketplace/app/mcp_tool_use/web/plugin/mcp_local_admin/static/scripts.js
mcp_marketplace-0.1.2.dist-info/METADATA
mcp_marketplace-0.1.2.dist-info/WHEEL
mcp_marketplace-0.1.2.dist-info/entry_points.txt
mcp_marketplace-0.1.2.dist-info/top_level.txt
mcp_marketplace-0.1.2.dist-info/RECORD
