Metadata-Version: 2.4
Name: mcp-marketplace
Version: 0.1.2
Summary: Open MCP Marketplace, MCP Registry, MCP client, OneKey MCP Router, MCP Tool Search of commercial MCPs
Author: deepnlp.org
Author-email: aihubadmin@126.com
Project-URL: Homepage, https://www.deepnlp.org/store/ai-agent/mcp-server
Project-URL: Repository, https://github.com/aiagenta2z/mcp-marketplace
Requires-Python: >=3.11
Requires-Dist: requests>=2.28.1
Requires-Dist: logging>=0.0.1
Requires-Dist: click>=8.0.3
Provides-Extra: mcp-tool-use
Requires-Dist: python-dotenv>=1.0.1; extra == "mcp-tool-use"
Requires-Dist: fastapi>=0.115.0; extra == "mcp-tool-use"
Requires-Dist: uvicorn[standard]>=0.29.0; extra == "mcp-tool-use"
Requires-Dist: pydantic>=2.7.0; extra == "mcp-tool-use"
Requires-Dist: asyncio>=3.4.3; extra == "mcp-tool-use"
Requires-Dist: openai>=1.0.0; extra == "mcp-tool-use"
Requires-Dist: anthropic>=0.25.0; extra == "mcp-tool-use"
Requires-Dist: mcp>=1.20.0; extra == "mcp-tool-use"
Requires-Dist: mcp-marketplace>=0.0.4; extra == "mcp-tool-use"
Requires-Dist: uuid>=1.30; extra == "mcp-tool-use"
Requires-Dist: python-dotenv>=1.0.1; extra == "mcp-tool-use"
Requires-Dist: httpx>=0.27.0; extra == "mcp-tool-use"
Requires-Dist: aiofiles>=23.2.1; extra == "mcp-tool-use"
Requires-Dist: anthropic>=0.25.0; extra == "mcp-tool-use"
Requires-Dist: Jinja2>=3.1.3; extra == "mcp-tool-use"
Provides-Extra: onekey-mcp-router
Provides-Extra: all
Requires-Dist: mcp-marketplace[mcp_tool_use]; extra == "all"
Requires-Dist: mcp-marketplace[onekey_mcp_router]; extra == "all"
